kozhindev_data_labeler/__init__.py
kozhindev_data_labeler/llm.py
kozhindev_data_labeler/llm_processor.py
kozhindev_data_labeler-0.0.2.dist-info/licenses/LICENCE
kozhindev_data_labeler-0.0.2.dist-info/METADATA
kozhindev_data_labeler-0.0.2.dist-info/WHEEL
kozhindev_data_labeler-0.0.2.dist-info/top_level.txt
kozhindev_data_labeler-0.0.2.dist-info/RECORD
