Metadata-Version: 2.4
Name: kozhindev_data_labeler
Version: 0.0.2
Summary: Пакет, содержащий класс для разметки данных, используя большие языковые модели
Author: YVoskanyan
Author-email: yuvoskanyan@team.kozhin.dev
Keywords: kozhindev_datalaber classification llm
Classifier: Programming Language :: Python :: 3.12
Classifier: License :: OSI Approved :: MIT License
Classifier: Operating System :: OS Independent
Requires-Python: >=3.12
License-File: LICENCE
Requires-Dist: pydantic>=2.11.7
Requires-Dist: litellm>=1.75.4
Dynamic: author
Dynamic: author-email
Dynamic: classifier
Dynamic: description
Dynamic: description-content-type
Dynamic: keywords
Dynamic: license-file
Dynamic: requires-dist
Dynamic: requires-python
Dynamic: summary
